cmlkit/README.md
cmlkit/__init__.py
cmlkit/dataset/README.md
cmlkit/dataset/__init__.py
cmlkit/dataset/dataset.py
cmlkit/dataset/dataset_loader.py
cmlkit/engine/README.md
cmlkit/engine/__init__.py
cmlkit/engine/cache/README.md
cmlkit/engine/cache/__init__.py
cmlkit/engine/cache/cache.py
cmlkit/engine/cache/cached.py
cmlkit/engine/cache/caches.py
cmlkit/engine/cache/disk.py
cmlkit/engine/cache/no.py
cmlkit/engine/caching.py
cmlkit/engine/component.py
cmlkit/engine/config.py
cmlkit/engine/configparse.py
cmlkit/engine/data/README.md
cmlkit/engine/data/__init__.py
cmlkit/engine/data/data.py
cmlkit/engine/hashing.py
cmlkit/engine/inout.py
cmlkit/env.py
cmlkit/evaluation/README.md
cmlkit/evaluation/__init__.py
cmlkit/evaluation/evaluator.py
cmlkit/evaluation/evaluator_holdout.py
cmlkit/evaluation/loss/README.md
cmlkit/evaluation/loss/__init__.py
cmlkit/evaluation/loss/loss.py
cmlkit/evaluation/loss/lossfs.py
cmlkit/exceptions.py
cmlkit/model.py
cmlkit/regression/README.md
cmlkit/regression/__init__.py
cmlkit/regression/data.py
cmlkit/regression/kernel.py
cmlkit/regression/qmml/README.md
cmlkit/regression/qmml/__init__.py
cmlkit/regression/qmml/kernel_atomic.py
cmlkit/regression/qmml/kernel_functions.py
cmlkit/regression/qmml/kernel_global.py
cmlkit/regression/qmml/krr.py
cmlkit/representation/README.md
cmlkit/representation/__init__.py
cmlkit/representation/composed.py
cmlkit/representation/coulomb_matrix.py
cmlkit/representation/data.py
cmlkit/representation/mbtr/README.md
cmlkit/representation/mbtr/__init__.py
cmlkit/representation/mbtr/mbtr.py
cmlkit/representation/mbtr/mbtrs.py
cmlkit/representation/mbtr/norm.py
cmlkit/representation/representation.py
cmlkit/representation/sf/README.md
cmlkit/representation/sf/__init__.py
cmlkit/representation/sf/config.py
cmlkit/representation/sf/parametrization.py
cmlkit/representation/sf/runner.py
cmlkit/representation/sf/runner_input.py
cmlkit/representation/sf/runner_output.py
cmlkit/representation/sf/sf.py
cmlkit-2.0.0a26.dist-info/LICENSE
cmlkit-2.0.0a26.dist-info/WHEEL
cmlkit-2.0.0a26.dist-info/METADATA
cmlkit-2.0.0a26.dist-info/RECORD
